Metadata-Version: 1.0
Name: travis-tester
Version: 0.0.12
Summary: Testing git and deployment stuff
Home-page: https://github.com/MatthewGilbert/testing
Author: Matthew Gilbert
Author-email: matthew.gilbert12@gmail.com
License: MIT
Platform: any
